MANIFEST.in
README.md
requirements.txt
setup.py
process_raw/__info__.py
process_raw/__init__.py
process_raw/process_raw.py
process_raw.egg-info/PKG-INFO
process_raw.egg-info/SOURCES.txt
process_raw.egg-info/dependency_links.txt
process_raw.egg-info/requires.txt
process_raw.egg-info/top_level.txt