Metadata-Version: 2.1
Name: process-raw
Version: 0.2.1
Summary: A python package to process raw and dng file, supporting demosaicing with gamma correction.
Home-page: https://github.com/DIYer22/process_raw
Author: DIYer22
Author-email: ylxx@live.com
License: UNKNOWN
Platform: UNKNOWN
Classifier: Topic :: Software Development :: Libraries :: Python Modules
Classifier: Programming Language :: Python :: 3
Classifier: License :: OSI Approved :: MIT License
Classifier: Operating System :: OS Independent
